airflow/providers/openlineage/__init__.py
airflow/providers/openlineage/conf.py
airflow/providers/openlineage/get_provider_info.py
airflow/providers/openlineage/sqlparser.py
airflow/providers/openlineage/version_compat.py
airflow/providers/openlineage/extractors/__init__.py
airflow/providers/openlineage/extractors/base.py
airflow/providers/openlineage/extractors/bash.py
airflow/providers/openlineage/extractors/manager.py
airflow/providers/openlineage/extractors/python.py
airflow/providers/openlineage/facets/AirflowDagRunFacet.json
airflow/providers/openlineage/facets/AirflowDebugRunFacet.json
airflow/providers/openlineage/facets/AirflowJobFacet.json
airflow/providers/openlineage/facets/AirflowRunFacet.json
airflow/providers/openlineage/facets/AirflowStateRunFacet.json
airflow/providers/openlineage/facets/__init__.py
airflow/providers/openlineage/operators/__init__.py
airflow/providers/openlineage/operators/empty.py
airflow/providers/openlineage/plugins/__init__.py
airflow/providers/openlineage/plugins/adapter.py
airflow/providers/openlineage/plugins/facets.py
airflow/providers/openlineage/plugins/listener.py
airflow/providers/openlineage/plugins/macros.py
airflow/providers/openlineage/plugins/openlineage.py
airflow/providers/openlineage/utils/__init__.py
airflow/providers/openlineage/utils/selective_enable.py
airflow/providers/openlineage/utils/spark.py
airflow/providers/openlineage/utils/sql.py
airflow/providers/openlineage/utils/utils.py
apache_airflow_providers_openlineage-2.10.0.dist-info/entry_points.txt
apache_airflow_providers_openlineage-2.10.0.dist-info/licenses/LICENSE
apache_airflow_providers_openlineage-2.10.0.dist-info/licenses/NOTICE
apache_airflow_providers_openlineage-2.10.0.dist-info/WHEEL
apache_airflow_providers_openlineage-2.10.0.dist-info/METADATA
apache_airflow_providers_openlineage-2.10.0.dist-info/RECORD
