Metadata-Version: 2.4
Name: apache-airflow-providers-openlineage
Version: 2.10.0
Summary: Provider package apache-airflow-providers-openlineage for Apache Airflow
Keywords: airflow-provider,openlineage,airflow,integration
Author-email: Apache Software Foundation <dev@airflow.apache.org>
Maintainer-email: Apache Software Foundation <dev@airflow.apache.org>
Requires-Python: >=3.10
License-Expression: Apache-2.0
Classifier: Development Status :: 5 - Production/Stable
Classifier: Environment :: Console
Classifier: Environment :: Web Environment
Classifier: Intended Audience :: Developers
Classifier: Intended Audience :: System Administrators
Classifier: Framework :: Apache Airflow
Classifier: Framework :: Apache Airflow :: Provider
Classifier: Programming Language :: Python :: 3.10
Classifier: Programming Language :: Python :: 3.11
Classifier: Programming Language :: Python :: 3.12
Classifier: Programming Language :: Python :: 3.13
Classifier: Topic :: System :: Monitoring
License-File: LICENSE
License-File: NOTICE
Requires-Dist: apache-airflow>=2.11.0
Requires-Dist: apache-airflow-providers-common-sql>=1.20.0
Requires-Dist: apache-airflow-providers-common-compat>=1.12.0
Requires-Dist: attrs>=22.2
Requires-Dist: openlineage-integration-common>=1.41.0
Requires-Dist: openlineage-python>=1.41.0
Requires-Dist: sqlalchemy>=1.4.49 ; extra == "sqlalchemy"
Project-URL: Bug Tracker, https://github.com/apache/airflow/issues
Project-URL: Changelog, https://airflow.apache.org/docs/apache-airflow-providers-openlineage/2.10.0/changelog.html
Project-URL: Documentation, https://airflow.apache.org/docs/apache-airflow-providers-openlineage/2.10.0
Project-URL: Mastodon, https://fosstodon.org/@airflow
Project-URL: Slack Chat, https://s.apache.org/airflow-slack
Project-URL: Source Code, https://github.com/apache/airflow
Project-URL: YouTube, https://www.youtube.com/channel/UCSXwxpWZQ7XZ1WL3wqevChA/
Provides-Extra: sqlalchemy
